_jpype.cpython-311-aarch64-linux-gnu.so
org.jpype.jar
jpype1_ext-0.0.2.dist-info/top_level.txt
jpype1_ext-0.0.2.dist-info/RECORD
jpype1_ext-0.0.2.dist-info/LICENSE
jpype1_ext-0.0.2.dist-info/entry_points.txt
jpype1_ext-0.0.2.dist-info/NOTICE
jpype1_ext-0.0.2.dist-info/METADATA
jpype1_ext-0.0.2.dist-info/AUTHORS.rst
jpype1_ext-0.0.2.dist-info/WHEEL
jpype/_jarray.py
jpype/_jexception.py
jpype/_jcollection.pyi
jpype/pickle.py
jpype/_core.py
jpype/_classpath.py
jpype/_jthread.py
jpype/_gui.py
jpype/__init__.py
jpype/_jproxy.py
jpype/_jmethod.py
jpype/nio.py
jpype/types.py
jpype/_jcollection.py
jpype/_jstring.py
jpype/protocol.py
jpype/_jpackage.py
jpype/_jio.py
jpype/_jobject.py
jpype/_jarray.pyi
jpype/_jio.pyi
jpype/dbapi2.py
jpype/_pykeywords.py
jpype/_jinit.py
jpype/config.py
jpype/_jvmfinder.py
jpype/_jcustomizer.py
jpype/_jclass.py
jpype/imports.py
jpype/beans.py
jpype/_pyinstaller/example.py
jpype/_pyinstaller/hook-jpype.py
jpype/_pyinstaller/entry_points.py
jpype/_pyinstaller/test_jpype_pyinstaller.py
