Metadata-Version: 2.1
Name: jpype1-ext
Version: 0.0.2
Summary: A Python to Java bridge - ext
Author-email: Steve Menard <devilwolf@users.sourceforge.net>
Maintainer-email: Luis Nell <cooperate@originell.org>, LocalStack Contributors <info@localstack.cloud>
License: License :: OSI Approved :: Apache Software License
Project-URL: homepage, https://github.com/localstack/jpype
Platform: Operating System :: Microsoft :: Windows
Platform: Operating System :: POSIX
Platform: Operating System :: Unix
Platform: Operating System :: MacOS
Classifier: Programming Language :: Python :: 3
Classifier: Programming Language :: Python :: 3.8
Classifier: Programming Language :: Python :: 3.9
Classifier: Programming Language :: Python :: 3.10
Classifier: Programming Language :: Python :: 3.11
Classifier: Programming Language :: Python :: 3.12
Classifier: Programming Language :: Python :: 3.13
Classifier: Topic :: Software Development
Classifier: Topic :: Scientific/Engineering
Requires-Python: >=3.8
License-File: LICENSE
License-File: NOTICE
License-File: AUTHORS.rst
Requires-Dist: packaging
Provides-Extra: docs
Requires-Dist: readthedocs-sphinx-ext; extra == "docs"
Requires-Dist: sphinx; extra == "docs"
Requires-Dist: sphinx-rtd-theme; extra == "docs"
Provides-Extra: tests
Requires-Dist: pytest; extra == "tests"
